src/__init__.py
src/daglit.py
src/digraph.py
src/digraph_todo.py
src/generators.py
src/layouts.py
daglit-0.0.1.dist-info/METADATA
daglit-0.0.1.dist-info/WHEEL
daglit-0.0.1.dist-info/top_level.txt
daglit-0.0.1.dist-info/RECORD
